pandas_npi/__init__.py
pandas_npi/utility_functions.py
pandas_npi/validate.py
pandas_npi-0.45.dist-info/METADATA
pandas_npi-0.45.dist-info/WHEEL
pandas_npi-0.45.dist-info/top_level.txt
pandas_npi-0.45.dist-info/RECORD
