Metadata-Version: 2.1
Name: pandas-npi
Version: 0.45
Summary: NPI validation made easy with Pandas.
Home-page: https://github.com/Lyonk71/pandas-npi
Author: Keith Lyons
Author-email: lyonk71@gmail.com
License: UNKNOWN
Platform: UNKNOWN
Requires-Dist: pandas
Requires-Dist: numpy
